backend/__init__.py
backend/inference_core/__init__.py
backend/inference_core/algorithms/dbscan.py
backend/inference_core/algorithms/kmeans.py
backend/inference_core/algorithms/linear_regression.py
backend/inference_core/algorithms/range.py
backend/inference_core/algorithms/skyline_algorithm.py
backend/inference_core/core.py
backend/inference_core/dataset_formatter.py
backend/inference_core/filter.py
backend/inference_core/prediction.py
backend/inference_core/prediction_stats.py
backend/inference_core/rankings.py
backend/inference_core/reapply/__init__.py
backend/inference_core/reapply/compare.py
backend/inference_core/reapply/cred.json
backend/inference_core/reapply/data_structures/Provenance/graph.py
backend/inference_core/reapply/data_structures/Provenance/node.py
backend/inference_core/reapply/data_structures/Provenance/state.py
backend/inference_core/reapply/data_structures/apply_results.py
backend/inference_core/reapply/data_structures/base_interaction.py
backend/inference_core/reapply/data_structures/brush.py
backend/inference_core/reapply/data_structures/brush_interaction.py
backend/inference_core/reapply/data_structures/filter_interaction.py
backend/inference_core/reapply/data_structures/interactions.py
backend/inference_core/reapply/data_structures/plot.py
backend/inference_core/reapply/data_structures/plot_interaction.py
backend/inference_core/reapply/data_structures/point_selection_interaction.py
backend/inference_core/reapply/data_structures/record.py
backend/inference_core/reapply/data_structures/select_prediction_interaction.py
backend/inference_core/reapply/data_structures/types.py
backend/inference_core/reapply/reapply.py
backend/inference_core/reapply/reapply_algorithms/algorithm_picker.py
backend/inference_core/reapply/reapply_algorithms/dbscan.py
backend/inference_core/reapply/reapply_algorithms/kmeans.py
backend/inference_core/reapply/reapply_algorithms/linear_regression.py
backend/inference_core/reapply/reapply_algorithms/range.py
reapply_workflows-0.1.0.dist-info/WHEEL
reapply_workflows-0.1.0.dist-info/METADATA
reapply_workflows-0.1.0.dist-info/RECORD
